
[{"content":"","date":"6 April 2026","externalUrl":null,"permalink":"/","section":"Portfolio - Hani Zaatar","summary":"","title":"Portfolio - Hani Zaatar","type":"page"},{"content":"","date":"6 April 2026","externalUrl":null,"permalink":"/projects/","section":"Projects","summary":"","title":"Projects","type":"projects"},{"content":"\rTides of Tomorrow\r#\rDigixArt Entertainment / THQ Nordic\r#\rUnrealEngine | C++ | Gameplay \u0026amp; UI Programmer\r#\rA narrative multiplayer adventure set on a post-apocalyptic ocean world where humanity struggles to survive on floating settlements.\nSteam \u0026ndash; PlayStation \u0026ndash; XBox\n","date":"6 April 2026","externalUrl":null,"permalink":"/projects/tidesoftomorrow/","section":"Projects","summary":"","title":"TidesOfTomorrow","type":"projects"},{"content":"","date":"6 April 2026","externalUrl":null,"permalink":"/tags/c++/","section":"Tags","summary":"","title":"C++","type":"tags"},{"content":"","date":"6 April 2026","externalUrl":null,"permalink":"/categories/","section":"Categories","summary":"","title":"Categories","type":"categories"},{"content":"","date":"6 April 2026","externalUrl":null,"permalink":"/tags/gameplay/","section":"Tags","summary":"","title":"Gameplay","type":"tags"},{"content":"","date":"6 April 2026","externalUrl":null,"permalink":"/categories/projects/","section":"Categories","summary":"","title":"Projects","type":"categories"},{"content":"","date":"6 April 2026","externalUrl":null,"permalink":"/tags/","section":"Tags","summary":"","title":"Tags","type":"tags"},{"content":"","date":"6 April 2026","externalUrl":null,"permalink":"/tags/unrealengine/","section":"Tags","summary":"","title":"UnrealEngine","type":"tags"},{"content":"\rWallrun Movement Mechanic\r#\rUnrealEngine | C++ | Gameplay Programmer\r#\rDeveloped a 3D Character wall run movement system which enables the player to perform vertical and horizontal wallrun on adjacent walls.\n","date":"6 April 2026","externalUrl":null,"permalink":"/projects/wallrunmovementmechanic/","section":"Projects","summary":"","title":"WallrunMovementMechanic","type":"projects"},{"content":"","externalUrl":null,"permalink":"/authors/","section":"Authors","summary":"","title":"Authors","type":"authors"},{"content":"","externalUrl":null,"permalink":"/series/","section":"Series","summary":"","title":"Series","type":"series"}]